mellon/__init__.py
mellon/_conditional.py
mellon/_cov.py
mellon/_derivatives.py
mellon/_inference.py
mellon/_parameters.py
mellon/_util.py
mellon/base_cov.py
mellon/base_model.py
mellon/base_predictor.py
mellon/compute_ls_time.py
mellon/conditional.py
mellon/cov.py
mellon/decomposition.py
mellon/density_estimator.py
mellon/derivatives.py
mellon/dimensionality_estimator.py
mellon/function_estimator.py
mellon/inference.py
mellon/model.py
mellon/parameter_validation.py
mellon/parameters.py
mellon/time_sensitive_density_estimator.py
mellon/util.py
mellon/validation.py
mellon/version.py
mellon-1.6.1.dist-info/licenses/LICENSE
mellon-1.6.1.dist-info/METADATA
mellon-1.6.1.dist-info/WHEEL
mellon-1.6.1.dist-info/entry_points.txt
mellon-1.6.1.dist-info/top_level.txt
mellon-1.6.1.dist-info/RECORD
