Metadata-Version: 2.4
Name: mellon
Version: 1.6.1
Summary: Non-parametric density estimator.
Author-email: Setty Lab <dominik.otto@gmail.com>
License: GNU General Public License v3.0
Project-URL: Homepage, https://github.com/settylab/mellon
Classifier: Intended Audience :: Science/Research
Classifier: License :: OSI Approved :: GNU General Public License v3 (GPLv3)
Requires-Python: >=3.6
License-File: LICENSE
Requires-Dist: jax
Requires-Dist: jaxopt
Requires-Dist: scikit-learn
Requires-Dist: pynndescent
Provides-Extra: dev
Requires-Dist: black; extra == "dev"
Requires-Dist: flake8; extra == "dev"
Requires-Dist: isort; extra == "dev"
Requires-Dist: mypy; extra == "dev"
Requires-Dist: pytest; extra == "dev"
Requires-Dist: pytest-cov; extra == "dev"
Requires-Dist: typing-extensions; extra == "dev"
Provides-Extra: docs
Requires-Dist: sphinxcontrib-autoprogram; extra == "docs"
Requires-Dist: sphinxcontrib-napoleon; extra == "docs"
Requires-Dist: sphinx-autodocgen; extra == "docs"
Requires-Dist: sphinx-github-style>=1.2.2; extra == "docs"
Requires-Dist: sphinx-mdinclude; extra == "docs"
Requires-Dist: m2r2; extra == "docs"
Requires-Dist: nbsphinx; extra == "docs"
Requires-Dist: furo; extra == "docs"
Requires-Dist: typing-extensions; extra == "docs"
Requires-Dist: IPython; extra == "docs"
Dynamic: license-file
